COPYING
LICENSE
MANIFEST.in
README.md
WARRANTY
setup.py
buildutils/__init__.py
buildutils/add_missing_license_headers.py
buildutils/codegeneration.py
buildutils/pom_template.xml
buildutils/__pycache__/__init__.cpython-36.pyc
buildutils/__pycache__/codegeneration.cpython-36.pyc
java/target/generated-sources/python/EventBuffer_pb2.pyi
java/target/generated-sources/python/events_pb2.pyi
javaresources/__init__.py
javaresources/python-matsim-instance-1.0-SNAPSHOT-jar-with-dependencies.jar
javawrappers/__init__.py
javawrappers/py.typed
javawrappers/au/__init__.py
javawrappers/au/com/__init__.py
javawrappers/au/com/objectix/__init__.py
javawrappers/au/com/objectix/jgridshift/__init__.py
javawrappers/au/com/objectix/jgridshift/_jgridshift.py
javawrappers/au/com/objectix/jgridshift/_jgridshift.pyi
javawrappers/com/__init__.py
javawrappers/com/fasterxml/__init__.py
javawrappers/com/fasterxml/classmate/__init__.py
javawrappers/com/fasterxml/classmate/_classmate.py
javawrappers/com/fasterxml/classmate/_classmate.pyi
javawrappers/com/fasterxml/classmate/members/__init__.py
javawrappers/com/fasterxml/classmate/members/_members.py
javawrappers/com/fasterxml/classmate/members/_members.pyi
javawrappers/com/fasterxml/classmate/types/__init__.py
javawrappers/com/fasterxml/classmate/types/_types.py
javawrappers/com/fasterxml/classmate/types/_types.pyi
javawrappers/com/fasterxml/classmate/util/__init__.py
javawrappers/com/fasterxml/classmate/util/_util.py
javawrappers/com/fasterxml/classmate/util/_util.pyi
javawrappers/com/google/__init__.py
javawrappers/com/google/common/__init__.py
javawrappers/com/google/common/annotations/__init__.py
javawrappers/com/google/common/annotations/_annotations.py
javawrappers/com/google/common/annotations/_annotations.pyi
javawrappers/com/google/common/base/__init__.py
javawrappers/com/google/common/base/_base.py
javawrappers/com/google/common/base/_base.pyi
javawrappers/com/google/common/base/internal/__init__.py
pythonmatsim.egg-info/PKG-INFO
pythonmatsim.egg-info/SOURCES.txt
pythonmatsim.egg-info/dependency_links.txt
pythonmatsim.egg-info/not-zip-safe
pythonmatsim.egg-info/requires.txt
pythonmatsim.egg-info/top_level.txt
