Metadata-Version: 2.1
Name: pythonmatsim
Version: 0.1.2
Summary: A package to use MATSim from Python
Home-page: https://github.com/matsim-eth/python-matsim
Author: Thibaut Dubernet
Author-email: thibaut.dubernet@ivt.baug.ethz.ch
License: GNU GPL 3.0
Platform: UNKNOWN
Classifier: Development Status :: 3 - Alpha
Classifier: Programming Language :: Java
Classifier: Programming Language :: Python :: 3.5
Classifier: Programming Language :: Python :: 3.6
Classifier: Programming Language :: Python :: 3.7
Classifier: License :: OSI Approved :: GNU General Public License v3 or later (GPLv3+)
Classifier: Operating System :: OS Independent
Requires-Python: >=3.6
